Workbook

Sheet Sheet1
A1: ETF DETAILS
A2: ='Daily Update'!B2 | B2: 46162
A4: ETF | B4: SYMBOL | C4: %age | D4: SYMBOL | E4: Acct Type | G4: Current Price | H4: Volume | I4: 1 Day Change % | J4: 5 Day Change % | K4: 1 Mos Change % | L4: 1 Year Change % | M4: 2 Year Change % | N4: 5 Year Change %
G5: =IF($B5="","",IFERROR(XLOOKUP($B5,'Daily Update'!$A:$A,'Daily Update'!$C:$C),"")) | H5: =IF($B5="","",IFERROR(XLOOKUP($B5,'Daily Update'!$A:$A,'Daily Update'!$D:$D),"")) | I5: =IF($B5="","",IFERROR(XLOOKUP($B5,'Daily Update'!$A:$A,'Daily Update'!$E:$E),"")) | J5: =IF($B5="","",IFERROR(XLOOKUP($B5,'Daily Update'!$A:$A,'Daily Update'!$F:$F),"")) | K5: =IF($B5="","",IFERROR(XLOOKUP($B5,'Daily Update'!$A:$A,'Daily Update'!$G:$G),"")) | L5: =IF($B5="","",IFERROR(XLOOKUP($B5,'Daily Update'!$A:$A,'Daily Update'!$H:$H),"")) | M5: =IF($B5="","",IFERROR(XLOOKUP($B5,'Daily Update'!$A:$A,'Daily Update'!$I:$I),"")) | N5: =IF($B5="","",IFERROR(XLOOKUP($B5,'Daily Update'!$A:$A,'Daily Update'!$J:$J),""))
A6: Berkshire Hathaway Inc | B6: BRKB | C6: 1 | D6: BRKB | E6: IRA | G6: 480.46 | H6: 5574031 | I6: -0.01621691 | J6: -0.00927912 | K6: 0.01238991 | L6: -0.06231586 | M6: 0.15234803 | N6: 0.67565296
G7: =IF($B7="","",IFERROR(XLOOKUP($B7,'Daily Update'!$A:$A,'Daily Update'!$C:$C),"")) | H7: =IF($B7="","",IFERROR(XLOOKUP($B7,'Daily Update'!$A:$A,'Daily Update'!$D:$D),"")) | I7: =IF($B7="","",IFERROR(XLOOKUP($B7,'Daily Update'!$A:$A,'Daily Update'!$E:$E),"")) | J7: =IF($B7="","",IFERROR(XLOOKUP($B7,'Daily Update'!$A:$A,'Daily Update'!$F:$F),"")) | K7: =IF($B7="","",IFERROR(XLOOKUP($B7,'Daily Update'!$A:$A,'Daily Update'!$G:$G),"")) | L7: =IF($B7="","",IFERROR(XLOOKUP($B7,'Daily Update'!$A:$A,'Daily Update'!$H:$H),"")) | M7: =IF($B7="","",IFERROR(XLOOKUP($B7,'Daily Update'!$A:$A,'Daily Update'!$I:$I),"")) | N7: =IF($B7="","",IFERROR(XLOOKUP($B7,'Daily Update'!$A:$A,'Daily Update'!$J:$J),""))
A8: ISHARES CORE HIGH DIVIDEND ETF | B8: HDV | C8: =SUM(C9:C19) | D8: HDV | E8: IRA | G8: 27.71 | H8: 2350436 | I8: 0.00471353 | J8: 0.01874994 | K8: 0.03441836 | L8: 0.22412885 | M8: 0.32704547 | N8: 0.68172165
A9: Merck & Co Inc | B9: MRK | C9: 0.0377 | D9: HDV | E9: IRA | G9: 114.24 | H9: 5209075 | I9: 0.01492538 | J9: 0.01664141 | K9: -0.04056439 | L9: 0.53295277 | M9: -0.07082237 | N9: 0.7590783
A10: Progressive Corp | B10: PGR | C10: 0.0379 | D10: HDV | E10: IRA | G10: 202.87 | H10: 2457538 | I10: -0.00553924 | J10: 0.02242716 | K10: 0.0014315 | L10: -0.25049085 | M10: 0.05375258 | N10: 1.223539
A11: Coca-Cola Co | B11: KO | C11: 0.0386 | D11: HDV | E11: IRA | G11: 81.92 | H11: 16586904 | I11: 0.00886701 | J11: 0.02361614 | K11: 0.08159494 | L11: 0.17189977 | M11: 0.37737433 | N11: 0.73980952
A12: The Home Depot Inc | B12: HD | C12: 0.0407 | D12: HDV | E12: IRA | G12: 302.44 | H12: 8678246 | I12: 0.00877224 | J12: -0.0258326 | K12: -0.13440181 | L12: -0.18265378 | M12: -0.07674027 | N12: 0.08184457
A13: Philip Morris International Inc | B13: PM | C13: 0.0417 | D13: HDV | E13: IRA | G13: 191.57 | H13: 3749166 | I13: 0.00036557 | J13: 0.02482221 | K13: 0.21408211 | L13: 0.14545238 | M13: 1.0761645 | N13: 1.4935167
A14: Procter & Gamble Co | B14: PG | C14: 0.0446 | D14: HDV | E14: IRA | G14: 141.3 | H14: 4715632 | I14: -0.00765501 | J14: -0.01813634 | K14: -0.03107603 | L14: -0.11777187 | M14: -0.11167802 | N14: 0.16290085
A15: AbbVie Inc | B15: ABBV | C15: 0.0544 | D15: HDV | E15: IRA | G15: 213.76 | H15: 4460380 | I15: 0.0207726 | J15: 0.02838446 | K15: 0.02581817 | L15: 0.1885406 | M15: 0.37448755 | N15: 1.2017402
A16: Johnson & Johnson | B16: JNJ | C16: 0.0568 | D16: HDV | E16: IRA | G16: 230 | H16: 6002888 | I16: 0.00471781 | J16: 0.02559532 | K16: -0.01784949 | L16: 0.5503196 | M16: 0.57780938 | N16: 0.54825663
A17: Chevron Corp | B17: CVX | C17: 0.0642 | D17: HDV | E17: IRA | G17: 197.25 | H17: 11811800 | I17: 0.0057618 | J17: 0.06076904 | K17: 0.0720691 | L17: 0.47047527 | M17: 0.30875537 | N17: 1.3171999
A18: Exxon Mobil Corp | B18: XOM | C18: 0.0842 | D18: HDV | E18: IRA | G18: 162.55 | H18: 20706800 | I18: 0.01283568 | J18: 0.08645887 | K18: 0.11754512 | L18: 0.57538721 | M18: 0.45085385 | N18: 2.3201354
A19: Other | B19: OTH | C19: =100%-(SUM(C9:C18)) | D19: HDV | E19: IRA | G19: =IF($B19="","",IFERROR(XLOOKUP($B19,'Daily Update'!$A:$A,'Daily Update'!$C:$C),"")) | H19: =IF($B19="","",IFERROR(XLOOKUP($B19,'Daily Update'!$A:$A,'Daily Update'!$D:$D),"")) | I19: =IF($B19="","",IFERROR(XLOOKUP($B19,'Daily Update'!$A:$A,'Daily Update'!$E:$E),"")) | J19: =IF($B19="","",IFERROR(XLOOKUP($B19,'Daily Update'!$A:$A,'Daily Update'!$F:$F),"")) | K19: =IF($B19="","",IFERROR(XLOOKUP($B19,'Daily Update'!$A:$A,'Daily Update'!$G:$G),"")) | L19: =IF($B19="","",IFERROR(XLOOKUP($B19,'Daily Update'!$A:$A,'Daily Update'!$H:$H),"")) | M19: =IF($B19="","",IFERROR(XLOOKUP($B19,'Daily Update'!$A:$A,'Daily Update'!$I:$I),"")) | N19: =IF($B19="","",IFERROR(XLOOKUP($B19,'Daily Update'!$A:$A,'Daily Update'!$J:$J),""))
G20: =IF($B20="","",IFERROR(XLOOKUP($B20,'Daily Update'!$A:$A,'Daily Update'!$C:$C),"")) | H20: =IF($B20="","",IFERROR(XLOOKUP($B20,'Daily Update'!$A:$A,'Daily Update'!$D:$D),"")) | I20: =IF($B20="","",IFERROR(XLOOKUP($B20,'Daily Update'!$A:$A,'Daily Update'!$E:$E),"")) | J20: =IF($B20="","",IFERROR(XLOOKUP($B20,'Daily Update'!$A:$A,'Daily Update'!$F:$F),"")) | K20: =IF($B20="","",IFERROR(XLOOKUP($B20,'Daily Update'!$A:$A,'Daily Update'!$G:$G),"")) | L20: =IF($B20="","",IFERROR(XLOOKUP($B20,'Daily Update'!$A:$A,'Daily Update'!$H:$H),"")) | M20: =IF($B20="","",IFERROR(XLOOKUP($B20,'Daily Update'!$A:$A,'Daily Update'!$I:$I),"")) | N20: =IF($B20="","",IFERROR(XLOOKUP($B20,'Daily Update'!$A:$A,'Daily Update'!$J:$J),""))
A21: WEDBUSH SERIES TRUST DAN IVES WEDBUSH AI REVOLUTION ETF | B21: IVES | C21: =SUM(C22:C32) | D21: IVES | E21: IRA | G21: 35.76 | H21: 399100 | I21: -0.01024087 | J21: -0.00556176 | K21: 0.09290944
A22: GE Vernova Inc | B22: GEV | C22: 0.0424 | D22: IVES | E22: IRA | G22: 1011.8 | H22: 2243200 | I22: -0.00044457 | J22: -0.0561391 | K22: 0.00902517 | L22: 1.2705348 | M22: 5.2449684
A23: Microsoft Corp | B23: MSFT | C23: 0.0444 | D23: IVES | E23: IRA | G23: 417.42 | H23: 32942800 | I23: -0.01444963 | J23: 0.02366536 | K23: -0.01270133 | L23: -0.08504617 | M23: 0.00679123 | N23: 0.76083236
A24: Micron Technology Inc | B24: MU | C24: 0.0466 | D24: IVES | E24: IRA | G24: 698.74 | H24: 61450300 | I24: 0.02523698 | J24: -0.08849699 | K24: 0.53545604 | L24: 6.0999745 | M24: 4.6161004 | N24: 7.8308338
A25: Apple Inc | B25: AAPL | C25: 0.0471 | D25: IVES | E25: IRA | G25: 298.97 | H25: 42199700 | I25: 0.003794 | J25: 0.01414523 | K25: 0.10737315 | L25: 0.43766669 | M25: 0.58824366 | N25: 1.4091896
A26: NVIDIA Corp | B26: NVDA | C26: 0.0484 | D26: IVES | E26: IRA | G26: 220.61 | H26: 140201600 | I26: -0.00769165 | J26: -0.00076999 | K26: 0.09386161 | L26: 0.62766095 | M26: 1.3868608 | N26: 14.135398
A27: Taiwan Semiconductor Manufacturing Co Ltd ADR | B27: TSM | C27: 0.0494 | D27: IVES | E27: IRA | G27: 392.61 | H27: 14054400 | I27: -0.00843548 | J27: -0.01175497 | K27: 0.05967607 | L27: 1.0541221 | M27: 1.657129 | N27: 2.7654654
A28: Alphabet Inc Class A | B28: GOOGL | C28: 0.0538 | D28: IVES | E28: IRA | G28: 387.66 | H28: 39458400 | I28: -0.02337884 | J28: 0.0008003 | K28: 0.13457039 | L28: 1.3358006 | M28: 1.2200616 | N28: 2.3885783
A29: Amazon.com Inc | B29: AMZN | C29: 0.0542 | D29: IVES | E29: IRA | G29: 259.34 | H29: 40269100 | I29: -0.02084116 | J29: -0.02437744 | K29: 0.0350415 | L29: 0.25795495 | M29: 0.40411478 | N29: 0.59707848
A30: Broadcom Inc | B30: AVGO | C30: 0.0544 | D30: IVES | E30: IRA | G30: 411.07 | H30: 20620900 | I30: -0.02291361 | J30: -0.01962791 | K30: 0.01114281 | L30: 0.79682048 | M30: 2.0063057 | N30: 8.9857326
A31: Advanced Micro Devices Inc | B31: AMD | C31: 0.0633 | D31: IVES | E31: IRA | G31: 414.05 | H31: 38637700 | I31: -0.01648496 | J31: -0.07637917 | K31: 0.48730186 | L31: 2.6085933 | M31: 1.5174803 | N31: 4.3042532
A32: Other | B32: OTH | C32: =100%-(SUM(C22:C31)) | D32: IVES | E32: IRA | G32: =IF($B32="","",IFERROR(XLOOKUP($B32,'Daily Update'!$A:$A,'Daily Update'!$C:$C),"")) | H32: =IF($B32="","",IFERROR(XLOOKUP($B32,'Daily Update'!$A:$A,'Daily Update'!$D:$D),"")) | I32: =IF($B32="","",IFERROR(XLOOKUP($B32,'Daily Update'!$A:$A,'Daily Update'!$E:$E),"")) | J32: =IF($B32="","",IFERROR(XLOOKUP($B32,'Daily Update'!$A:$A,'Daily Update'!$F:$F),"")) | K32: =IF($B32="","",IFERROR(XLOOKUP($B32,'Daily Update'!$A:$A,'Daily Update'!$G:$G),"")) | L32: =IF($B32="","",IFERROR(XLOOKUP($B32,'Daily Update'!$A:$A,'Daily Update'!$H:$H),"")) | M32: =IF($B32="","",IFERROR(XLOOKUP($B32,'Daily Update'!$A:$A,'Daily Update'!$I:$I),"")) | N32: =IF($B32="","",IFERROR(XLOOKUP($B32,'Daily Update'!$A:$A,'Daily Update'!$J:$J),""))
G33: =IF($B33="","",IFERROR(XLOOKUP($B33,'Daily Update'!$A:$A,'Daily Update'!$C:$C),"")) | H33: =IF($B33="","",IFERROR(XLOOKUP($B33,'Daily Update'!$A:$A,'Daily Update'!$D:$D),"")) | I33: =IF($B33="","",IFERROR(XLOOKUP($B33,'Daily Update'!$A:$A,'Daily Update'!$E:$E),"")) | J33: =IF($B33="","",IFERROR(XLOOKUP($B33,'Daily Update'!$A:$A,'Daily Update'!$F:$F),"")) | K33: =IF($B33="","",IFERROR(XLOOKUP($B33,'Daily Update'!$A:$A,'Daily Update'!$G:$G),"")) | L33: =IF($B33="","",IFERROR(XLOOKUP($B33,'Daily Update'!$A:$A,'Daily Update'!$H:$H),"")) | M33: =IF($B33="","",IFERROR(XLOOKUP($B33,'Daily Update'!$A:$A,'Daily Update'!$I:$I),"")) | N33: =IF($B33="","",IFERROR(XLOOKUP($B33,'Daily Update'!$A:$A,'Daily Update'!$J:$J),""))
A34: NEOS ETF TR NEOS RUSSELL 2000 HIGH INCOME ETF | B34: IWMI | C34: =SUM(C35:C36) | D34: IWMI | E34: IRA | G34: 50.4 | H34: 338400 | I34: -0.00923919 | J34: -0.02740251 | K34: -0.00467414 | L34: 0.29223417
A35: First American Treasury Obligs X | B35: FXFXX | C35: 0.0044925277 | D35: IWMI | E35: IRA | G35: 1
A36: Vanguard Russell 2000 ETF | B36: VTWO | C36: 0.99550747 | D36: IWMI | E36: IRA | G36: 110.32 | H36: 2337100 | I36: -0.01067171 | J36: -0.03380628 | K36: -0.00996142 | L36: 0.32343842 | M36: 0.3467783 | N36: 0.33418223
G37: =IF($B37="","",IFERROR(XLOOKUP($B37,'Daily Update'!$A:$A,'Daily Update'!$C:$C),"")) | H37: =IF($B37="","",IFERROR(XLOOKUP($B37,'Daily Update'!$A:$A,'Daily Update'!$D:$D),"")) | I37: =IF($B37="","",IFERROR(XLOOKUP($B37,'Daily Update'!$A:$A,'Daily Update'!$E:$E),"")) | J37: =IF($B37="","",IFERROR(XLOOKUP($B37,'Daily Update'!$A:$A,'Daily Update'!$F:$F),"")) | K37: =IF($B37="","",IFERROR(XLOOKUP($B37,'Daily Update'!$A:$A,'Daily Update'!$G:$G),"")) | L37: =IF($B37="","",IFERROR(XLOOKUP($B37,'Daily Update'!$A:$A,'Daily Update'!$H:$H),"")) | M37: =IF($B37="","",IFERROR(XLOOKUP($B37,'Daily Update'!$A:$A,'Daily Update'!$I:$I),"")) | N37: =IF($B37="","",IFERROR(XLOOKUP($B37,'Daily Update'!$A:$A,'Daily Update'!$J:$J),""))
A38: LISTED FUNDS TRUST ROUNDHILL MAGNIFICENT SEVEN ETF | B38: MAGS | C38: =SUM(C39:C49) | D38: MAGS | E38: IRA | G38: 68.53 | H38: 2829500 | I38: -0.01338901 | J38: -0.00853594 | K38: 0.03130176 | L38: 0.33032396 | M38: 0.71899593
A39: United States Treasury Bills 0% | C39: 0.4212 | D39: MAGS | E39: IRA | G39: =IF($B39="","",IFERROR(XLOOKUP($B39,'Daily Update'!$A:$A,'Daily Update'!$C:$C),"")) | H39: =IF($B39="","",IFERROR(XLOOKUP($B39,'Daily Update'!$A:$A,'Daily Update'!$D:$D),"")) | I39: =IF($B39="","",IFERROR(XLOOKUP($B39,'Daily Update'!$A:$A,'Daily Update'!$E:$E),"")) | J39: =IF($B39="","",IFERROR(XLOOKUP($B39,'Daily Update'!$A:$A,'Daily Update'!$F:$F),"")) | K39: =IF($B39="","",IFERROR(XLOOKUP($B39,'Daily Update'!$A:$A,'Daily Update'!$G:$G),"")) | L39: =IF($B39="","",IFERROR(XLOOKUP($B39,'Daily Update'!$A:$A,'Daily Update'!$H:$H),"")) | M39: =IF($B39="","",IFERROR(XLOOKUP($B39,'Daily Update'!$A:$A,'Daily Update'!$I:$I),"")) | N39: =IF($B39="","",IFERROR(XLOOKUP($B39,'Daily Update'!$A:$A,'Daily Update'!$J:$J),""))
A40: Meta Platforms Inc Class A | B40: META | C40: 0.0531 | D40: MAGS | E40: IRA | G40: 602.61 | H40: 11720900 | I40: -0.01407051 | J40: -0.00064679 | K40: -0.12481302 | L40: -0.05611858 | M40: 0.28561643 | N40: 0.90621436
A41: ALPHABET INC-CL A SWAP | C41: 0.0531 | D41: MAGS | E41: IRA | G41: =IF($B41="","",IFERROR(XLOOKUP($B41,'Daily Update'!$A:$A,'Daily Update'!$C:$C),"")) | H41: =IF($B41="","",IFERROR(XLOOKUP($B41,'Daily Update'!$A:$A,'Daily Update'!$D:$D),"")) | I41: =IF($B41="","",IFERROR(XLOOKUP($B41,'Daily Update'!$A:$A,'Daily Update'!$E:$E),"")) | J41: =IF($B41="","",IFERROR(XLOOKUP($B41,'Daily Update'!$A:$A,'Daily Update'!$F:$F),"")) | K41: =IF($B41="","",IFERROR(XLOOKUP($B41,'Daily Update'!$A:$A,'Daily Update'!$G:$G),"")) | L41: =IF($B41="","",IFERROR(XLOOKUP($B41,'Daily Update'!$A:$A,'Daily Update'!$H:$H),"")) | M41: =IF($B41="","",IFERROR(XLOOKUP($B41,'Daily Update'!$A:$A,'Daily Update'!$I:$I),"")) | N41: =IF($B41="","",IFERROR(XLOOKUP($B41,'Daily Update'!$A:$A,'Daily Update'!$J:$J),""))
A42: Microsoft Corp | B42: MSFT | C42: 0.0544 | D42: MAGS | E42: IRA | G42: 417.42 | H42: 32942800 | I42: -0.01444963 | J42: 0.02366536 | K42: -0.01270133 | L42: -0.08504617 | M42: 0.00679123 | N42: 0.76083236
A43: AMAZON.COM INC SWAP | C43: 0.055 | D43: MAGS | E43: IRA | G43: =IF($B43="","",IFERROR(XLOOKUP($B43,'Daily Update'!$A:$A,'Daily Update'!$C:$C),"")) | H43: =IF($B43="","",IFERROR(XLOOKUP($B43,'Daily Update'!$A:$A,'Daily Update'!$D:$D),"")) | I43: =IF($B43="","",IFERROR(XLOOKUP($B43,'Daily Update'!$A:$A,'Daily Update'!$E:$E),"")) | J43: =IF($B43="","",IFERROR(XLOOKUP($B43,'Daily Update'!$A:$A,'Daily Update'!$F:$F),"")) | K43: =IF($B43="","",IFERROR(XLOOKUP($B43,'Daily Update'!$A:$A,'Daily Update'!$G:$G),"")) | L43: =IF($B43="","",IFERROR(XLOOKUP($B43,'Daily Update'!$A:$A,'Daily Update'!$H:$H),"")) | M43: =IF($B43="","",IFERROR(XLOOKUP($B43,'Daily Update'!$A:$A,'Daily Update'!$I:$I),"")) | N43: =IF($B43="","",IFERROR(XLOOKUP($B43,'Daily Update'!$A:$A,'Daily Update'!$J:$J),""))
A44: Alphabet Inc Class A | B44: GOOGL | C44: 0.0552 | D44: MAGS | E44: IRA | G44: 387.66 | H44: 39458400 | I44: -0.02337884 | J44: 0.0008003 | K44: 0.13457039 | L44: 1.3358006 | M44: 1.2200616 | N44: 2.3885783
A45: NVIDIA Corp | B45: NVDA | C45: 0.0567 | D45: MAGS | E45: IRA | G45: 220.61 | H45: 140201600 | I45: -0.00769165 | J45: -0.00076999 | K45: 0.09386161 | L45: 0.62766095 | M45: 1.3868608 | N45: 14.135398
A46: ALPHABET INC SWAP GS | C46: 0.0585 | D46: MAGS | E46: IRA | G46: =IF($B46="","",IFERROR(XLOOKUP($B46,'Daily Update'!$A:$A,'Daily Update'!$C:$C),"")) | H46: =IF($B46="","",IFERROR(XLOOKUP($B46,'Daily Update'!$A:$A,'Daily Update'!$D:$D),"")) | I46: =IF($B46="","",IFERROR(XLOOKUP($B46,'Daily Update'!$A:$A,'Daily Update'!$E:$E),"")) | J46: =IF($B46="","",IFERROR(XLOOKUP($B46,'Daily Update'!$A:$A,'Daily Update'!$F:$F),"")) | K46: =IF($B46="","",IFERROR(XLOOKUP($B46,'Daily Update'!$A:$A,'Daily Update'!$G:$G),"")) | L46: =IF($B46="","",IFERROR(XLOOKUP($B46,'Daily Update'!$A:$A,'Daily Update'!$H:$H),"")) | M46: =IF($B46="","",IFERROR(XLOOKUP($B46,'Daily Update'!$A:$A,'Daily Update'!$I:$I),"")) | N46: =IF($B46="","",IFERROR(XLOOKUP($B46,'Daily Update'!$A:$A,'Daily Update'!$J:$J),""))
A47: Amazon.com Inc | B47: AMZN | C47: 0.0627 | D47: MAGS | E47: IRA | G47: 259.34 | H47: 40269100 | I47: -0.02084116 | J47: -0.02437744 | K47: 0.0350415 | L47: 0.25795495 | M47: 0.40411478 | N47: 0.59707848
A48: Roundhill Ultra Shrt Dur No Div TrgtETF | B48: XBOX | C48: 0.078 | D48: MAGS | E48: IRA | G48: 99.53 | H48: 32700 | I48: 0 | J48: 0.00090503 | K48: 0.00241714
A49: Other | B49: OTH | C49: =100%-(SUM(C39:C48)) | D49: MAGS | E49: IRA | G49: =IF($B49="","",IFERROR(XLOOKUP($B49,'Daily Update'!$A:$A,'Daily Update'!$C:$C),"")) | H49: =IF($B49="","",IFERROR(XLOOKUP($B49,'Daily Update'!$A:$A,'Daily Update'!$D:$D),"")) | I49: =IF($B49="","",IFERROR(XLOOKUP($B49,'Daily Update'!$A:$A,'Daily Update'!$E:$E),"")) | J49: =IF($B49="","",IFERROR(XLOOKUP($B49,'Daily Update'!$A:$A,'Daily Update'!$F:$F),"")) | K49: =IF($B49="","",IFERROR(XLOOKUP($B49,'Daily Update'!$A:$A,'Daily Update'!$G:$G),"")) | L49: =IF($B49="","",IFERROR(XLOOKUP($B49,'Daily Update'!$A:$A,'Daily Update'!$H:$H),"")) | M49: =IF($B49="","",IFERROR(XLOOKUP($B49,'Daily Update'!$A:$A,'Daily Update'!$I:$I),"")) | N49: =IF($B49="","",IFERROR(XLOOKUP($B49,'Daily Update'!$A:$A,'Daily Update'!$J:$J),""))
G50: =IF($B50="","",IFERROR(XLOOKUP($B50,'Daily Update'!$A:$A,'Daily Update'!$C:$C),"")) | H50: =IF($B50="","",IFERROR(XLOOKUP($B50,'Daily Update'!$A:$A,'Daily Update'!$D:$D),"")) | I50: =IF($B50="","",IFERROR(XLOOKUP($B50,'Daily Update'!$A:$A,'Daily Update'!$E:$E),"")) | J50: =IF($B50="","",IFERROR(XLOOKUP($B50,'Daily Update'!$A:$A,'Daily Update'!$F:$F),"")) | K50: =IF($B50="","",IFERROR(XLOOKUP($B50,'Daily Update'!$A:$A,'Daily Update'!$G:$G),"")) | L50: =IF($B50="","",IFERROR(XLOOKUP($B50,'Daily Update'!$A:$A,'Daily Update'!$H:$H),"")) | M50: =IF($B50="","",IFERROR(XLOOKUP($B50,'Daily Update'!$A:$A,'Daily Update'!$I:$I),"")) | N50: =IF($B50="","",IFERROR(XLOOKUP($B50,'Daily Update'!$A:$A,'Daily Update'!$J:$J),""))
A51: NEOS ETF TRUST NEOS NASDAQ 100 HIGH INCOME ETF | B51: QQQI | C51: =SUM(C52:C61) | D51: QQQI | E51: IRA | G51: 56.14 | H51: 7640900 | I51: -0.00354989 | J51: -0.00319603 | K51: 0.05412315 | L51: 0.2700307 | M51: 0.46685149
A52: Meta Platforms Inc Class A | B52: META | C52: 0.0329 | D52: QQQI | E52: IRA | G52: 602.61 | H52: 11720900 | I52: -0.01407051 | J52: -0.00064679 | K52: -0.12481302 | L52: -0.05611858 | M52: 0.28561643 | N52: 0.90621436
A53: Tesla Inc | B53: TSLA | C53: 0.0337 | D53: QQQI | E53: IRA | G53: 404.11 | H53: 46354700 | I53: -0.01434183 | J53: -0.06768953 | K53: 0.00871147 | L53: 0.18129729 | M53: 1.2771891 | N53: 1.0660723
A54: Broadcom Inc | B54: AVGO | C54: 0.0365 | D54: QQQI | E54: IRA | G54: 411.07 | H54: 20620900 | I54: -0.02291361 | J54: -0.01962791 | K54: 0.01114281 | L54: 0.79682048 | M54: 2.0063057 | N54: 8.9857326
A55: Alphabet Inc Class C | B55: GOOG | C55: 0.0381 | D55: QQQI | E55: IRA | G55: 384.9 | H55: 25497700 | I55: -0.02088472 | J55: 0.00281378 | K55: 0.13406011 | L55: 1.3007722 | M55: 1.1888433 | N55: 2.2941019
A56: Alphabet Inc Class A | B56: GOOGL | C56: 0.0412 | D56: QQQI | E56: IRA | G56: 387.66 | H56: 39458400 | I56: -0.02337884 | J56: 0.0008003 | K56: 0.13457039 | L56: 1.3358006 | M56: 1.2200616 | N56: 2.3885783
A57: Amazon.com Inc | B57: AMZN | C57: 0.0518 | D57: QQQI | E57: IRA | G57: 259.34 | H57: 40269100 | I57: -0.02084116 | J57: -0.02437744 | K57: 0.0350415 | L57: 0.25795495 | M57: 0.40411478 | N57: 0.59707848
A58: Microsoft Corp | B58: MSFT | C58: 0.0553 | D58: QQQI | E58: IRA | G58: 417.42 | H58: 32942800 | I58: -0.01444963 | J58: 0.02366536 | K58: -0.01270133 | L58: -0.08504617 | M58: 0.00679123 | N58: 0.76083236
A59: Apple Inc | B59: AAPL | C59: 0.0707 | D59: QQQI | E59: IRA | G59: 298.97 | H59: 42199700 | I59: 0.003794 | J59: 0.01414523 | K59: 0.10737315 | L59: 0.43766669 | M59: 0.58824366 | N59: 1.4091896
A60: NVIDIA Corp | B60: NVDA | C60: 0.0857 | D60: QQQI | E60: IRA | G60: 220.61 | H60: 140201600 | I60: -0.00769165 | J60: -0.00076999 | K60: 0.09386161 | L60: 0.62766095 | M60: 1.3868608 | N60: 14.135398
A61: Other | B61: OTH | C61: =100%-(SUM(C52:C60)) | D61: QQQI | E61: IRA | G61: =IF($B61="","",IFERROR(XLOOKUP($B61,'Daily Update'!$A:$A,'Daily Update'!$C:$C),"")) | H61: =IF($B61="","",IFERROR(XLOOKUP($B61,'Daily Update'!$A:$A,'Daily Update'!$D:$D),"")) | I61: =IF($B61="","",IFERROR(XLOOKUP($B61,'Daily Update'!$A:$A,'Daily Update'!$E:$E),"")) | J61: =IF($B61="","",IFERROR(XLOOKUP($B61,'Daily Update'!$A:$A,'Daily Update'!$F:$F),"")) | K61: =IF($B61="","",IFERROR(XLOOKUP($B61,'Daily Update'!$A:$A,'Daily Update'!$G:$G),"")) | L61: =IF($B61="","",IFERROR(XLOOKUP($B61,'Daily Update'!$A:$A,'Daily Update'!$H:$H),"")) | M61: =IF($B61="","",IFERROR(XLOOKUP($B61,'Daily Update'!$A:$A,'Daily Update'!$I:$I),"")) | N61: =IF($B61="","",IFERROR(XLOOKUP($B61,'Daily Update'!$A:$A,'Daily Update'!$J:$J),""))
G62: =IF($B62="","",IFERROR(XLOOKUP($B62,'Daily Update'!$A:$A,'Daily Update'!$C:$C),"")) | H62: =IF($B62="","",IFERROR(XLOOKUP($B62,'Daily Update'!$A:$A,'Daily Update'!$D:$D),"")) | I62: =IF($B62="","",IFERROR(XLOOKUP($B62,'Daily Update'!$A:$A,'Daily Update'!$E:$E),"")) | J62: =IF($B62="","",IFERROR(XLOOKUP($B62,'Daily Update'!$A:$A,'Daily Update'!$F:$F),"")) | K62: =IF($B62="","",IFERROR(XLOOKUP($B62,'Daily Update'!$A:$A,'Daily Update'!$G:$G),"")) | L62: =IF($B62="","",IFERROR(XLOOKUP($B62,'Daily Update'!$A:$A,'Daily Update'!$H:$H),"")) | M62: =IF($B62="","",IFERROR(XLOOKUP($B62,'Daily Update'!$A:$A,'Daily Update'!$I:$I),"")) | N62: =IF($B62="","",IFERROR(XLOOKUP($B62,'Daily Update'!$A:$A,'Daily Update'!$J:$J),""))
A63: ETF SER SOLUTIONS DEFIANCE QUANTUM ETF | B63: QTUM | C63: =SUM(C64:C72) | D63: QTUM | E63: IRA | G63: 140.63 | H63: 528600 | I63: -0.00943859 | J63: -0.02326706 | K63: 0.0996169 | L63: 0.67591539 | M63: 1.3275651 | N63: 2.1806808
A64: Coherent Corp | B64: COHR | C64: 0.0177 | D64: QTUM | E64: IRA | G64: 353.63 | H64: 5771600 | I64: -0.02535618 | J64: -0.05449053 | K64: 0.02495512 | L64: 3.4549007 | M64: 5.0834337 | N64: 4.3669754
A65: Onto Innovation Inc | B65: ONTO | C65: 0.0181 | D65: QTUM | E65: IRA | G65: 248.08 | H65: 4992400 | I65: -0.02534081 | J65: -0.10743326 | K65: -0.14678775 | L65: 1.4704243 | M65: 0.10997764 | N65: 2.8780678
A66: Marvell Technology Inc | B66: MRVL | C66: 0.0184 | D66: QTUM | E66: IRA | G66: 176.27 | H66: 24916400 | I66: 0.04345002 | J66: 0.07155018 | K66: 0.26186557 | L66: 1.8252325 | M66: 1.4656723 | N66: 2.8849938
A67: ON Semiconductor Corp | B67: ON | C67: 0.0189 | D67: QTUM | E67: IRA | G67: 106.02 | H67: 11707700 | I67: -0.03116151 | J67: 0.01834594 | K67: 0.27719545 | L67: 1.4183393 | M67: 0.44895448 | N67: 1.7516221
A68: Micron Technology Inc | B68: MU | C68: 0.0202 | D68: QTUM | E68: IRA | G68: 698.74 | H68: 61450300 | I68: 0.02523698 | J68: -0.08849699 | K68: 0.53545604 | L68: 6.0999745 | M68: 4.6161004 | N68: 7.8308338
A69: Nokia Oyj ADR | B69: NOK | C69: 0.0214 | D69: QTUM | E69: IRA | G69: 13.67 | H69: 82194000 | I69: -0.00509459 | J69: 0.03796507 | K69: 0.32589714 | L69: 1.6378822 | M69: 2.6478265 | N69: 1.9549765
A70: STMicroelectronics NV ADR | B70: STM | C70: 0.0216 | D70: QTUM | E70: IRA | G70: 61.23 | H70: 10716400 | I70: 0.00442914 | J70: 0.05696529 | K70: 0.38466752 | L70: 1.4003457 | M70: 0.5079717 | N70: 0.76566413
A71: Intel Corp | B71: INTC | C71: 0.0239 | D71: QTUM | E71: IRA | G71: 110.8 | H71: 149436900 | I71: 0.02431363 | J71: -0.08133652 | K71: 0.61751829 | L71: 4.1824138 | M71: 2.5030749 | N71: 1.1640348
A72: Other | B72: OTH | C72: =100%-(SUM(C64:C71)) | D72: QTUM | E72: IRA | G72: =IF($B72="","",IFERROR(XLOOKUP($B72,'Daily Update'!$A:$A,'Daily Update'!$C:$C),"")) | H72: =IF($B72="","",IFERROR(XLOOKUP($B72,'Daily Update'!$A:$A,'Daily Update'!$D:$D),"")) | I72: =IF($B72="","",IFERROR(XLOOKUP($B72,'Daily Update'!$A:$A,'Daily Update'!$E:$E),"")) | J72: =IF($B72="","",IFERROR(XLOOKUP($B72,'Daily Update'!$A:$A,'Daily Update'!$F:$F),"")) | K72: =IF($B72="","",IFERROR(XLOOKUP($B72,'Daily Update'!$A:$A,'Daily Update'!$G:$G),"")) | L72: =IF($B72="","",IFERROR(XLOOKUP($B72,'Daily Update'!$A:$A,'Daily Update'!$H:$H),"")) | M72: =IF($B72="","",IFERROR(XLOOKUP($B72,'Daily Update'!$A:$A,'Daily Update'!$I:$I),"")) | N72: =IF($B72="","",IFERROR(XLOOKUP($B72,'Daily Update'!$A:$A,'Daily Update'!$J:$J),""))
G73: =IF($B73="","",IFERROR(XLOOKUP($B73,'Daily Update'!$A:$A,'Daily Update'!$C:$C),"")) | H73: =IF($B73="","",IFERROR(XLOOKUP($B73,'Daily Update'!$A:$A,'Daily Update'!$D:$D),"")) | I73: =IF($B73="","",IFERROR(XLOOKUP($B73,'Daily Update'!$A:$A,'Daily Update'!$E:$E),"")) | J73: =IF($B73="","",IFERROR(XLOOKUP($B73,'Daily Update'!$A:$A,'Daily Update'!$F:$F),"")) | K73: =IF($B73="","",IFERROR(XLOOKUP($B73,'Daily Update'!$A:$A,'Daily Update'!$G:$G),"")) | L73: =IF($B73="","",IFERROR(XLOOKUP($B73,'Daily Update'!$A:$A,'Daily Update'!$H:$H),"")) | M73: =IF($B73="","",IFERROR(XLOOKUP($B73,'Daily Update'!$A:$A,'Daily Update'!$I:$I),"")) | N73: =IF($B73="","",IFERROR(XLOOKUP($B73,'Daily Update'!$A:$A,'Daily Update'!$J:$J),""))
A74: SCHWAB STRATEGIC TR US DIVIDEND EQUITY ETF | B74: SCHD | C74: =SUM(C75:C85) | D74: SCHD | E74: IRA | G74: 32.1 | H74: 18035400 | I74: 0.00187258 | J74: 0.01070523 | K74: 0.0338164 | L74: 0.25432877 | M74: 0.29702091 | N74: 0.49969627
A75: Verizon Communications Inc | B75: VZ | C75: 0.0366 | D75: SCHD | E75: IRA | G75: 47.74 | H75: 24582600 | I75: 0.02095816 | J75: -0.00396409 | K75: 0.02556396 | L75: 0.15001212 | M75: 0.35774616 | N75: 0.1465749
A76: Merck & Co Inc | B76: MRK | C76: 0.0371 | D76: SCHD | E76: IRA | G76: 114.24 | H76: 5209075 | I76: 0.01492538 | J76: 0.01664141 | K76: -0.04056439 | L76: 0.53295277 | M76: -0.07082237 | N76: 0.7590783
A77: Procter & Gamble Co | B77: PG | C77: 0.0372 | D77: SCHD | E77: IRA | G77: 141.3 | H77: 4715632 | I77: -0.00765501 | J77: -0.01813634 | K77: -0.03107603 | L77: -0.11777187 | M77: -0.11167802 | N77: 0.16290085
A78: PepsiCo Inc | B78: PEP | C78: 0.0381 | D78: SCHD | E78: IRA | G78: 150.37 | H78: 10091200 | I78: 0.00878839 | J78: -0.00974653 | K78: -0.04629925 | L78: 0.18668612 | M78: -0.11303928 | N78: 0.19273985
A79: Coca-Cola Co | B79: KO | C79: 0.0406 | D79: SCHD | E79: IRA | G79: 81.92 | H79: 16586904 | I79: 0.00886701 | J79: 0.02361614 | K79: 0.08159494 | L79: 0.17189977 | M79: 0.37737433 | N79: 0.73980952
A80: ConocoPhillips | B80: COP | C80: 0.0407 | D80: SCHD | E80: IRA | G80: 125.11 | H80: 6026700 | I80: 0.00457684 | J80: 0.06142358 | K80: 0.08617526 | L80: 0.42967363 | M80: 0.09514642 | N80: 1.6995754
A81: Chevron Corp | B81: CVX | C81: 0.0416 | D81: SCHD | E81: IRA | G81: 197.25 | H81: 11811800 | I81: 0.0057618 | J81: 0.06076904 | K81: 0.0720691 | L81: 0.47047527 | M81: 0.30875537 | N81: 1.3171999
A82: Qualcomm Inc | B82: QCOM | C82: 0.0431 | D82: SCHD | E82: IRA | G82: 195.61 | H82: 19576900 | I82: -0.03943233 | J82: -0.06989681 | K82: 0.43619681 | L82: 0.30249367 | M82: 0.05336134 | N82: 0.64514805
A83: UnitedHealth Group Inc | B83: UNH | C83: 0.0511 | D83: SCHD | E83: IRA | G83: 389.24 | H83: 5007700 | I83: -0.00483219 | J83: -0.01803785 | K83: 0.19902654 | L83: 0.26694696 | M83: -0.22494655 | N83: 0.037749
A84: Texas Instruments Inc | B84: TXN | C84: 0.0535 | D84: SCHD | E84: IRA | G84: 302.31 | H84: 7295000 | I84: 0.00568859 | J84: 0.0241894 | K84: 0.32210441 | L84: 0.65015058 | M84: 0.64037904 | N84: 0.88057441
A85: Other | B85: OTH | C85: =100%-(SUM(C75:C84)) | D85: SCHD | E85: IRA | G85: =IF($B85="","",IFERROR(XLOOKUP($B85,'Daily Update'!$A:$A,'Daily Update'!$C:$C),"")) | H85: =IF($B85="","",IFERROR(XLOOKUP($B85,'Daily Update'!$A:$A,'Daily Update'!$D:$D),"")) | I85: =IF($B85="","",IFERROR(XLOOKUP($B85,'Daily Update'!$A:$A,'Daily Update'!$E:$E),"")) | J85: =IF($B85="","",IFERROR(XLOOKUP($B85,'Daily Update'!$A:$A,'Daily Update'!$F:$F),"")) | K85: =IF($B85="","",IFERROR(XLOOKUP($B85,'Daily Update'!$A:$A,'Daily Update'!$G:$G),"")) | L85: =IF($B85="","",IFERROR(XLOOKUP($B85,'Daily Update'!$A:$A,'Daily Update'!$H:$H),"")) | M85: =IF($B85="","",IFERROR(XLOOKUP($B85,'Daily Update'!$A:$A,'Daily Update'!$I:$I),"")) | N85: =IF($B85="","",IFERROR(XLOOKUP($B85,'Daily Update'!$A:$A,'Daily Update'!$J:$J),""))
G86: =IF($B86="","",IFERROR(XLOOKUP($B86,'Daily Update'!$A:$A,'Daily Update'!$C:$C),"")) | H86: =IF($B86="","",IFERROR(XLOOKUP($B86,'Daily Update'!$A:$A,'Daily Update'!$D:$D),"")) | I86: =IF($B86="","",IFERROR(XLOOKUP($B86,'Daily Update'!$A:$A,'Daily Update'!$E:$E),"")) | J86: =IF($B86="","",IFERROR(XLOOKUP($B86,'Daily Update'!$A:$A,'Daily Update'!$F:$F),"")) | K86: =IF($B86="","",IFERROR(XLOOKUP($B86,'Daily Update'!$A:$A,'Daily Update'!$G:$G),"")) | L86: =IF($B86="","",IFERROR(XLOOKUP($B86,'Daily Update'!$A:$A,'Daily Update'!$H:$H),"")) | M86: =IF($B86="","",IFERROR(XLOOKUP($B86,'Daily Update'!$A:$A,'Daily Update'!$I:$I),"")) | N86: =IF($B86="","",IFERROR(XLOOKUP($B86,'Daily Update'!$A:$A,'Daily Update'!$J:$J),""))
A87: INVESCO EXCHANGE TRADED FD TR II S&P 500 MOMENTUM ETF | B87: SPMO | C87: =SUM(C88:C98) | D87: SPMO | E87: IRA | G87: 140.63 | H87: 2165600 | I87: -0.00558615 | J87: -0.02644508 | K87: 0.0961029 | L87: 0.34798128 | M87: 0.76661297 | N87: 1.7400274
A88: Caterpillar Inc | B88: CAT | C88: 0.0297 | D88: SPMO | E88: IRA | G88: 860.15 | H88: 3238900 | I88: -0.00439839 | J88: -0.05699782 | K88: 0.08448699 | L88: 1.4660608 | M88: 1.4800923 | N88: 3.0030655
A89: Advanced Micro Devices Inc | B89: AMD | C89: 0.032 | D89: SPMO | E89: IRA | G89: 414.05 | H89: 38637700 | I89: -0.01648496 | J89: -0.07637917 | K89: 0.48730186 | L89: 2.6085933 | M89: 1.5174803 | N89: 4.3042532
A90: Lam Research Corp | B90: LRCX | C90: 0.0322 | D90: SPMO | E90: IRA | G90: 273.38 | H90: 8303700 | I90: -0.01647714 | J90: -0.05483331 | K90: 0.0215994 | L90: 2.2854099 | M90: 2.0526677 | N90: 3.6010969
A91: Exxon Mobil Corp | B91: XOM | C91: 0.0332 | D91: SPMO | E91: IRA | G91: 162.55 | H91: 20706800 | I91: 0.01283568 | J91: 0.08645887 | K91: 0.11754512 | L91: 0.57538721 | M91: 0.45085385 | N91: 2.3201354
A92: Alphabet Inc Class C | B92: GOOG | C92: 0.0435 | D92: SPMO | E92: IRA | G92: 384.9 | H92: 25497700 | I92: -0.02088472 | J92: 0.00281378 | K92: 0.13406011 | L92: 1.3007722 | M92: 1.1888433 | N92: 2.2941019
A93: Johnson & Johnson | B93: JNJ | C93: 0.0442 | D93: SPMO | E93: IRA | G93: 230 | H93: 6002888 | I93: 0.00471781 | J93: 0.02559532 | K93: -0.01784949 | L93: 0.5503196 | M93: 0.57780938 | N93: 0.54825663
A94: Alphabet Inc Class A | B94: GOOGL | C94: 0.0547 | D94: SPMO | E94: IRA | G94: 387.66 | H94: 39458400 | I94: -0.02337884 | J94: 0.0008003 | K94: 0.13457039 | L94: 1.3358006 | M94: 1.2200616 | N94: 2.3885783
A95: Micron Technology Inc | B95: MU | C95: 0.0642 | D95: SPMO | E95: IRA | G95: 698.74 | H95: 61450300 | I95: 0.02523698 | J95: -0.08849699 | K95: 0.53545604 | L95: 6.0999745 | M95: 4.6161004 | N95: 7.8308338
A96: Broadcom Inc | B96: AVGO | C96: 0.0796 | D96: SPMO | E96: IRA | G96: 411.07 | H96: 20620900 | I96: -0.02291361 | J96: -0.01962791 | K96: 0.01114281 | L96: 0.79682048 | M96: 2.0063057 | N96: 8.9857326
A97: NVIDIA Corp | B97: NVDA | C97: 0.0899 | D97: SPMO | E97: IRA | G97: 220.61 | H97: 140201600 | I97: -0.00769165 | J97: -0.00076999 | K97: 0.09386161 | L97: 0.62766095 | M97: 1.3868608 | N97: 14.135398
A98: Other | B98: OTH | C98: =100%-(SUM(C88:C97)) | D98: SPMO | E98: IRA | G98: =IF($B98="","",IFERROR(XLOOKUP($B98,'Daily Update'!$A:$A,'Daily Update'!$C:$C),"")) | H98: =IF($B98="","",IFERROR(XLOOKUP($B98,'Daily Update'!$A:$A,'Daily Update'!$D:$D),"")) | I98: =IF($B98="","",IFERROR(XLOOKUP($B98,'Daily Update'!$A:$A,'Daily Update'!$E:$E),"")) | J98: =IF($B98="","",IFERROR(XLOOKUP($B98,'Daily Update'!$A:$A,'Daily Update'!$F:$F),"")) | K98: =IF($B98="","",IFERROR(XLOOKUP($B98,'Daily Update'!$A:$A,'Daily Update'!$G:$G),"")) | L98: =IF($B98="","",IFERROR(XLOOKUP($B98,'Daily Update'!$A:$A,'Daily Update'!$H:$H),"")) | M98: =IF($B98="","",IFERROR(XLOOKUP($B98,'Daily Update'!$A:$A,'Daily Update'!$I:$I),"")) | N98: =IF($B98="","",IFERROR(XLOOKUP($B98,'Daily Update'!$A:$A,'Daily Update'!$J:$J),""))
G99: =IF($B99="","",IFERROR(XLOOKUP($B99,'Daily Update'!$A:$A,'Daily Update'!$C:$C),"")) | H99: =IF($B99="","",IFERROR(XLOOKUP($B99,'Daily Update'!$A:$A,'Daily Update'!$D:$D),"")) | I99: =IF($B99="","",IFERROR(XLOOKUP($B99,'Daily Update'!$A:$A,'Daily Update'!$E:$E),"")) | J99: =IF($B99="","",IFERROR(XLOOKUP($B99,'Daily Update'!$A:$A,'Daily Update'!$F:$F),"")) | K99: =IF($B99="","",IFERROR(XLOOKUP($B99,'Daily Update'!$A:$A,'Daily Update'!$G:$G),"")) | L99: =IF($B99="","",IFERROR(XLOOKUP($B99,'Daily Update'!$A:$A,'Daily Update'!$H:$H),"")) | M99: =IF($B99="","",IFERROR(XLOOKUP($B99,'Daily Update'!$A:$A,'Daily Update'!$I:$I),"")) | N99: =IF($B99="","",IFERROR(XLOOKUP($B99,'Daily Update'!$A:$A,'Daily Update'!$J:$J),""))
A100: STATE STREET SPDR S&P 500 ETF TRUST UNITS | B100: SPY | C100: =SUM(C101:C111) | D100: SPY | E100: IRA | G100: 733.73 | H100: 54129800 | I100: -0.00666086 | J100: -0.00602836 | K100: 0.03321875 | L100: 0.24761062 | M100: 0.41956137 | N100: 0.89171758
A101: Berkshire Hathaway Inc Class B | B101: BRK.B | C101: 0.0141 | D101: SPY | E101: IRA | G101: 480.46 | H101: 5586100 | I101: -0.01621691 | J101: -0.00927912 | K101: 0.01238991 | L101: -0.06231586 | M101: 0.15234803 | N101: 0.67565296
...

Sheet Daily Update
A1: Daily ETF / Holding Update Interface
A2: Workbook last updated: | B2: 46162
A3: Enter or paste today's market data into the yellow columns. Sheet1 columns G:N will update automatically by matching each row's SYMBOL. Leave unavailable fields blank.
A5: Ticker | B5: Security / ETF Name | C5: Current Price | D5: Volume | E5: 1 Day Change % | F5: 5 Day Change % | G5: 1 Mos Change % | H5: 1 Year Change % | I5: 2 Year Change % | J5: 5 Year Change % | K5: Last Updated | L5: Source / Notes
A6: BRKB | B6: Berkshire Hathaway Inc | C6: 480.46 | D6: 5586100 | E6: -0.01621691 | F6: -0.00927912 | G6: 0.01238991 | H6: -0.06231586 | I6: 0.15234803 | J6: 0.67565296 | K6: 2026-05-20 04:13 | L6: yfinance
A7: HDV | B7: ISHARES CORE HIGH DIVIDEND ETF | C7: 27.71 | D7: 2370100 | E7: 0.00471353 | F7: 0.01874994 | G7: 0.03441836 | H7: 0.22412885 | I7: 0.32704534 | J7: 0.68172185 | K7: 2026-05-20 04:13 | L7: yfinance
A8: MRK | B8: Merck & Co Inc | C8: 114.24 | D8: 7550400 | E8: 0.01492538 | F8: 0.01664141 | G8: -0.04056439 | H8: 0.53295262 | I8: -0.07082231 | J8: 0.75907851 | K8: 2026-05-20 04:13 | L8: yfinance
A9: PGR | B9: Progressive Corp | C9: 202.87 | D9: 2577200 | E9: -0.00553924 | F9: 0.02242716 | G9: 0.0014315 | H9: -0.25049085 | I9: 0.05375258 | J9: 1.223539 | K9: 2026-05-20 04:13 | L9: yfinance
A10: KO | B10: Coca-Cola Co | C10: 81.92 | D10: 16587900 | E10: 0.00886701 | F10: 0.02361614 | G10: 0.08159494 | H10: 0.1718999 | I10: 0.37737398 | J10: 0.73981008 | K10: 2026-05-20 04:13 | L10: yfinance
A11: HD | B11: The Home Depot Inc | C11: 302.44 | D11: 8682700 | E11: 0.00877224 | F11: -0.0258326 | G11: -0.13440181 | H11: -0.18265385 | I11: -0.07674018 | J11: 0.08184457 | K11: 2026-05-20 04:13 | L11: yfinance
A12: PM | B12: Philip Morris International Inc | C12: 191.57 | D12: 5741500 | E12: 0.00036557 | F12: 0.02482221 | G12: 0.21408211 | H12: 0.14545249 | I12: 1.0761647 | J12: 1.4935167 | K12: 2026-05-20 04:13 | L12: yfinance
A13: PG | B13: Procter & Gamble Co | C13: 141.3 | D13: 8351900 | E13: -0.00765501 | F13: -0.01813634 | G13: -0.03107603 | H13: -0.11777178 | I13: -0.11167793 | J13: 0.16290077 | K13: 2026-05-20 04:13 | L13: yfinance
A14: ABBV | B14: AbbVie Inc | C14: 213.76 | D14: 7217400 | E14: 0.0207726 | F14: 0.02838446 | G14: 0.02581817 | H14: 0.1885406 | I14: 0.37448755 | J14: 1.2017404 | K14: 2026-05-20 04:13 | L14: yfinance
A15: JNJ | B15: Johnson & Johnson | C15: 230 | D15: 9668500 | E15: 0.00471781 | F15: 0.02559532 | G15: -0.01784949 | H15: 0.5503196 | I15: 0.57780938 | J15: 0.54825631 | K15: 2026-05-20 04:13 | L15: yfinance
A16: CVX | B16: Chevron Corp | C16: 197.25 | D16: 11811800 | E16: 0.0057618 | F16: 0.06076904 | G16: 0.0720691 | H16: 0.47047543 | I16: 0.30875551 | J16: 1.3172001 | K16: 2026-05-20 04:13 | L16: yfinance
A17: XOM | B17: Exxon Mobil Corp | C17: 162.55 | D17: 20706800 | E17: 0.01283568 | F17: 0.08645887 | G17: 0.11754512 | H17: 0.57538721 | I17: 0.45085385 | J17: 2.3201362 | K17: 2026-05-20 04:13 | L17: yfinance
A18: IVES | B18: WEDBUSH SERIES TRUST DAN IVES WEDBUSH AI REVOLUTION ETF | C18: 35.76 | D18: 399100 | E18: -0.01024087 | F18: -0.00556176 | G18: 0.09290944 | K18: 2026-05-20 04:13 | L18: yfinance
A19: GEV | B19: GE Vernova Inc | C19: 1011.8 | D19: 2243200 | E19: -0.00044457 | F19: -0.0561391 | G19: 0.00902517 | H19: 1.2705349 | I19: 5.2449684 | K19: 2026-05-20 04:13 | L19: yfinance
A20: MSFT | B20: Microsoft Corp | C20: 417.42 | D20: 32942800 | E20: -0.01444963 | F20: 0.02366536 | G20: -0.01270133 | H20: -0.08504617 | I20: 0.00679138 | J20: 0.76083213 | K20: 2026-05-20 04:13 | L20: yfinance
A21: MU | B21: Micron Technology Inc | C21: 698.74 | D21: 61450300 | E21: 0.02523698 | F21: -0.08849699 | G21: 0.53545604 | H21: 6.0999745 | I21: 4.6161004 | J21: 7.8308329 | K21: 2026-05-20 04:13 | L21: yfinance
A22: AAPL | B22: Apple Inc | C22: 298.97 | D22: 42199700 | E22: 0.003794 | F22: 0.01414523 | G22: 0.10737315 | H22: 0.43766669 | I22: 0.58824353 | J22: 1.40919 | K22: 2026-05-20 04:13 | L22: yfinance
A23: NVDA | B23: NVIDIA Corp | C23: 220.61 | D23: 140201600 | E23: -0.00769165 | F23: -0.00076999 | G23: 0.09386161 | H23: 0.62766095 | I23: 1.3868611 | J23: 14.1354 | K23: 2026-05-20 04:13 | L23: yfinance
A24: TSM | B24: Taiwan Semiconductor Manufacturing Co Ltd ADR | C24: 392.61 | D24: 14054400 | E24: -0.00843548 | F24: -0.01175497 | G24: 0.05967607 | H24: 1.0541225 | I24: 1.657129 | J24: 2.7654654 | K24: 2026-05-20 04:13 | L24: yfinance
A25: GOOGL | B25: Alphabet Inc Class A | C25: 387.66 | D25: 39458400 | E25: -0.02337884 | F25: 0.0008003 | G25: 0.13457039 | H25: 1.3358006 | I25: 1.220061 | J25: 2.3885778 | K25: 2026-05-20 04:13 | L25: yfinance
A26: AMZN | B26: Amazon.com Inc | C26: 259.34 | D26: 40269100 | E26: -0.02084116 | F26: -0.02437744 | G26: 0.0350415 | H26: 0.25795495 | I26: 0.40411478 | J26: 0.59707848 | K26: 2026-05-20 04:13 | L26: yfinance
A27: AVGO | B27: Broadcom Inc | C27: 411.07 | D27: 20620900 | E27: -0.02291361 | F27: -0.01962791 | G27: 0.01114281 | H27: 0.79682048 | I27: 2.006306 | J27: 8.9857308 | K27: 2026-05-20 04:13 | L27: yfinance
A28: AMD | B28: Advanced Micro Devices Inc | C28: 414.05 | D28: 38637700 | E28: -0.01648496 | F28: -0.07637917 | G28: 0.48730186 | H28: 2.6085933 | I28: 1.5174803 | J28: 4.3042532 | K28: 2026-05-20 04:13 | L28: yfinance
A29: IWMI | B29: NEOS ETF TR NEOS RUSSELL 2000 HIGH INCOME ETF | C29: 50.4 | D29: 338400 | E29: -0.00923919 | F29: -0.02740251 | G29: -0.00467414 | H29: 0.29223429 | K29: 2026-05-20 04:13 | L29: yfinance
A30: FXFXX | B30: First American Treasury Obligs X | C30: 1 | K30: 2026-05-20 04:13 | L30: fixed $1.00
A31: VTWO | B31: Vanguard Russell 2000 ETF | C31: 110.32 | D31: 2337100 | E31: -0.01067171 | F31: -0.03380628 | G31: -0.00996142 | H31: 0.32343854 | I31: 0.3467783 | J31: 0.33418223 | K31: 2026-05-20 04:13 | L31: yfinance
A32: MAGS | B32: LISTED FUNDS TRUST ROUNDHILL MAGNIFICENT SEVEN ETF | C32: 68.53 | D32: 2829500 | E32: -0.01338901 | F32: -0.00853594 | G32: 0.03130176 | H32: 0.33032396 | I32: 0.71899593 | K32: 2026-05-20 04:13 | L32: yfinance
A33: META | B33: Meta Platforms Inc Class A | C33: 602.61 | D33: 11720900 | E33: -0.01407051 | F33: -0.00064679 | G33: -0.12481302 | H33: -0.05611858 | I33: 0.28561635 | J33: 0.90621418 | K33: 2026-05-20 04:13 | L33: yfinance
A34: XBOX | B34: Roundhill Ultra Shrt Dur No Div TrgtETF | C34: 99.53 | D34: 32700 | E34: 0 | F34: 0.00090503 | G34: 0.00241714 | K34: 2026-05-20 04:13 | L34: yfinance
A35: QQQI | B35: NEOS ETF TRUST NEOS NASDAQ 100 HIGH INCOME ETF | C35: 56.14 | D35: 7640900 | E35: -0.00354989 | F35: -0.00319603 | G35: 0.05412315 | H35: 0.2700307 | I35: 0.46685105 | K35: 2026-05-20 04:13 | L35: yfinance
A36: TSLA | B36: Tesla Inc | C36: 404.11 | D36: 46354700 | E36: -0.01434183 | F36: -0.06768953 | G36: 0.00871147 | H36: 0.18129729 | I36: 1.2771891 | J36: 1.0660723 | K36: 2026-05-20 04:13 | L36: yfinance
A37: GOOG | B37: Alphabet Inc Class C | C37: 384.9 | D37: 25497700 | E37: -0.02088472 | F37: 0.00281378 | G37: 0.13406011 | H37: 1.3007722 | I37: 1.1888433 | J37: 2.2941017 | K37: 2026-05-20 04:13 | L37: yfinance
A38: QTUM | B38: ETF SER SOLUTIONS DEFIANCE QUANTUM ETF | C38: 140.63 | D38: 528600 | E38: -0.00943859 | F38: -0.02326706 | G38: 0.0996169 | H38: 0.67591539 | I38: 1.3275651 | J38: 2.1806808 | K38: 2026-05-20 04:13 | L38: yfinance
A39: COHR | B39: Coherent Corp | C39: 353.63 | D39: 5771600 | E39: -0.02535618 | F39: -0.05449053 | G39: 0.02495512 | H39: 3.4549007 | I39: 5.0834337 | J39: 4.3669754 | K39: 2026-05-20 04:13 | L39: yfinance
A40: ONTO | B40: Onto Innovation Inc | C40: 248.08 | D40: 4992400 | E40: -0.02534081 | F40: -0.10743326 | G40: -0.14678775 | H40: 1.4704243 | I40: 0.10997764 | J40: 2.8780678 | K40: 2026-05-20 04:13 | L40: yfinance
A41: MRVL | B41: Marvell Technology Inc | C41: 176.27 | D41: 24916400 | E41: 0.04345002 | F41: 0.07155018 | G41: 0.26186557 | H41: 1.8252325 | I41: 1.4656723 | J41: 2.8849935 | K41: 2026-05-20 04:13 | L41: yfinance
A42: ON | B42: ON Semiconductor Corp | C42: 106.02 | D42: 11707700 | E42: -0.03116151 | F42: 0.01834594 | G42: 0.27719545 | H42: 1.4183393 | I42: 0.44895448 | J42: 1.7516221 | K42: 2026-05-20 04:13 | L42: yfinance
A43: NOK | B43: Nokia Oyj ADR | C43: 13.67 | D43: 82194000 | E43: -0.00509459 | F43: 0.03796507 | G43: 0.32589714 | H43: 1.6378822 | I43: 2.6478268 | J43: 1.9549765 | K43: 2026-05-20 04:13 | L43: yfinance
A44: STM | B44: STMicroelectronics NV ADR | C44: 61.23 | D44: 10716400 | E44: 0.00442914 | F44: 0.05696529 | G44: 0.38466752 | H44: 1.4003459 | I44: 0.50797156 | J44: 0.76566432 | K44: 2026-05-20 04:13 | L44: yfinance
A45: INTC | B45: Intel Corp | C45: 110.8 | D45: 149436900 | E45: 0.02431363 | F45: -0.08133652 | G45: 0.61751829 | H45: 4.1824138 | I45: 2.5030749 | J45: 1.1640348 | K45: 2026-05-20 04:13 | L45: yfinance
A46: SCHD | B46: SCHWAB STRATEGIC TR US DIVIDEND EQUITY ETF | C46: 32.1 | D46: 18035400 | E46: 0.00187258 | F46: 0.01070523 | G46: 0.0338164 | H46: 0.25432877 | I46: 0.29702111 | J46: 0.49969627 | K46: 2026-05-20 04:13 | L46: yfinance
A47: VZ | B47: Verizon Communications Inc | C47: 47.74 | D47: 24582600 | E47: 0.02095816 | F47: -0.00396409 | G47: 0.02556396 | H47: 0.15001222 | I47: 0.35774645 | J47: 0.14657511 | K47: 2026-05-20 04:13 | L47: yfinance
... A57: BRK.B | B57: Berkshire Hathaway Inc Class B | C57: 480.46 | D57: 5586100 | E57: -0.01621691 | F57: -0.00927912 | G57: 0.01238991 | H57: -0.06231586 | I57: 0.15234803 | J57: 0.67565296 | K57: 2026-05-20 04:13 | L57: yfinance
A58: SPYI | B58: SHP ETF TR NEOS S&P 500 HIGH INCOME ETF | C58: 53.33 | D58: 3214400 | E58: -0.00392228 | F58: -0.00243167 | G58: 0.02513559 | H58: 0.21245062 | I58: 0.36003277 | K58: 2026-05-20 04:13 | L58: yfinance
A59: VTV | B59: VANGUARD INDEX FUNDS VANGUARD VALUE ETF | C59: 207.08 | D59: 2317300 | E59: -0.00144663 | F59: -0.00685815 | G59: 0.01390519 | H59: 0.22040706 | I59: 0.32286755 | J59: 0.68208848 | K59: 2026-05-20 04:13 | L59: yfinance
A60: WMT | B60: Walmart Inc | C60: 134.2 | D60: 16943100 | E60: 0.00644968 | F60: 0.02953579 | G60: 0.05455769 | H60: 0.37914812 | I60: 1.1146427 | J60: 2.013154 | K60: 2026-05-20 04:13 | L60: yfinance
A61: JPM | B61: JPMorgan Chase & Co | C61: 295.7 | D61: 8062500 | E61: -0.01672596 | F61: -0.03011018 | G61: -0.04702052 | H61: 0.13806554 | I61: 0.50613826 | J61: 1.0862153 | K61: 2026-05-20 04:13 | L61: yfinance
A62: CGDV | B62: CAPITAL GROUP DIVIDEND VALUE ETF | C62: 47.3 | D62: 3302800 | E62: -0.00838578 | F62: -0.00379108 | G62: 0.02870813 | H62: 0.2850915 | I62: 0.46729892 | K62: 2026-05-20 04:13 | L62: yfinance
A63: LLY | B63: Eli Lilly and Co | C63: 1021.41 | D63: 3792500 | E63: 0.03372157 | F63: 0.03363901 | G63: 0.10370563 | H63: 0.36223261 | I63: 0.34503312 | J63: 4.3663834 | K63: 2026-05-20 04:13 | L63: yfinance
A64: GE | B64: GE Aerospace | C64: 285.28 | D64: 5237500 | E64: -0.00248257 | F64: -0.04091448 | G64: -0.06198009 | H64: 0.21887887 | I64: 0.80565262 | J64: 3.4865976 | K64: 2026-05-20 04:13 | L64: yfinance
A65: RTX | B65: RTX Corp | C65: 174.49 | D65: 5576000 | E65: -0.00829776 | F65: -0.02459609 | G65: -0.11164847 | H65: 0.29326186 | I65: 0.73010849 | J65: 1.2759816 | K65: 2026-05-20 04:13 | L65: yfinance
A66: AMAT | B66: Applied Materials Inc | C66: 406.91 | D66: 8412100 | E66: -0.01610369 | F66: -0.05633119 | G66: 0.02511715 | H66: 1.474088 | I66: 0.95212861 | J66: 2.2586212 | K66: 2026-05-20 04:13 | L66: yfinance
A67: CARR | B67: Carrier Global Corp Ordinary Shares | C67: 61.44 | D67: 7208600 | E67: -0.04758957 | F67: -0.06284318 | G67: 0.00552579 | H67: -0.17783885 | I67: -0.03252263 | J67: 0.50113577 | K67: 2026-05-20 04:13 | L67: yfinance
A68: DIVO | B68: AMPLIFY ETF TR AMPLIFY CWP ENHANCED DIVIDEND INCOME ETF | C68: 45.5 | D68: 601600 | E68: -0.00241177 | F68: -0.00219295 | G68: -0.01313364 | H68: 0.16784289 | I68: 0.29841771 | J68: 0.64779686 | K68: 2026-05-20 04:13 | L68: yfinance
A69: V | B69: Visa Inc Class A | C69: 329.91 | D69: 12855800 | E69: -0.0082071 | F69: 0.01069172 | G69: 0.04281733 | H69: -0.09617854 | I69: 0.19576281 | J69: 0.51244838 | K69: 2026-05-20 04:13 | L69: yfinance
A70: SOFR | B70: Amplify Samsung SOFR ETF | C70: 100.32 | D70: 8400 | E70: 0.00014954 | F70: 0.00049868 | G70: 0.00323521 | H70: 0.03980704 | I70: 0.08981407 | K70: 2026-05-20 04:13 | L70: yfinance
A71: TJX | B71: TJX Companies Inc | C71: 150.68 | D71: 8725100 | E71: 0.00286185 | F71: 0.0060797 | G71: -0.05916399 | H71: 0.12954169 | I71: 0.54041122 | J71: 1.4055427 | K71: 2026-05-20 04:13 | L71: yfinance
A72: GS | B72: The Goldman Sachs Group Inc | C72: 928.74 | D72: 1758000 | E72: -0.0186187 | F72: -0.01814149 | G72: 0.0030131 | H72: 0.54822915 | I72: 1.0715236 | J72: 1.9108587 | K72: 2026-05-20 04:13 | L72: yfinance
A73: AXP | B73: American Express Co | C73: 309.31 | D73: 2917400 | E73: -0.00938378 | F73: -0.01590786 | G73: -0.06747265 | H73: 0.04427737 | I73: 0.30173448 | J73: 1.1130981 | K73: 2026-05-20 04:13 | L73: yfinance
A74: FDRXX | B74: Fidelity Phillips Street Trust - Fidelity Cash Reserves | C74: 1 | K74: 2026-05-20 04:13 | L74: fixed $1.00
A75: AIQ | B75: GLOBAL X FUNDS GLOBAL X ARTIFICIAL INTELLIGENCE & TECHNOLOGY ETF | C75: 60.4 | D75: 2304900 | E75: -0.00527009 | F75: -0.01016059 | G75: 0.11645108 | H75: 0.48045589 | I75: 0.7670942 | J75: 1.156788 | K75: 2026-05-20 04:13 | L75: yfinance
A76: CSCO | B76: Cisco Systems Inc | C76: 115.38 | D76: 32497400 | E76: -0.02944145 | F76: 0.16205052 | G76: 0.3377391 | H76: 0.84661679 | I76: 1.5239886 | J76: 1.5188093 | K76: 2026-05-20 04:13 | L76: yfinance
A77: ARKQ | B77: ARK ETF TR AUTONOMOUS TECHNOLOGY & ROBOTICS ETF | C77: 129.62 | D77: 172000 | E77: -0.01474614 | F77: -0.04339487 | G77: -0.00154069 | H77: 0.64538891 | I77: 1.3127393 | J77: 0.67156576 | K77: 2026-05-20 04:13 | L77: yfinance
A78: PLTR | B78: Palantir Technologies Inc Ordinary Shares - Class A | C78: 135.26 | D78: 29701300 | E78: 0.00088793 | F78: -0.00544122 | G78: -0.07602982 | H78: 0.07068782 | I78: 5.2159923 | J78: 5.5628331 | K78: 2026-05-20 04:13 | L78: yfinance
A79: DE | B79: Deere & Co | C79: 558.07 | D79: 1027900 | E79: -0.01137307 | F79: -0.05281827 | G79: -0.05485556 | H79: 0.06710465 | I79: 0.44521826 | J79: 0.67777037 | K79: 2026-05-20 04:13 | L79: yfinance
A80: RKLB | B80: Rocket Lab Corp | C80: 127.31 | D80: 29996300 | E80: -0.02935351 | F80: 0.08293637 | G80: 0.50129709 | H80: 3.9344962 | I80: 28.955294 | J80: 11.782128 | K80: 2026-05-20 04:13 | L80: yfinance
A81: KTOS | B81: Kratos Defense & Security Solutions Inc | C81: 53.47 | D81: 2747900 | E81: -0.01383253 | F81: -0.0673295 | G81: -0.24679528 | H81: 0.52206091 | I81: 1.5425582 | J81: 1.2307052 | K81: 2026-05-20 04:13 | L81: yfinance
A82: TER | B82: Teradyne Inc | C82: 321.52 | D82: 3486200 | E82: 0.00146395 | F82: -0.10302698 | G82: -0.15474004 | H82: 2.9611106 | I82: 1.456213 | J82: 1.5902986 | K82: 2026-05-20 04:13 | L82: yfinance
A83: SMH | B83: VANECK ETF TR VANECK SEMICONDUCTOR ETF | C83: 543.96 | D83: 11882000 | E83: -0.00402803 | F83: -0.0308062 | G83: 0.17192351 | H83: 1.2180099 | I83: 1.3803303 | J83: 3.6840163 | K83: 2026-05-20 04:13 | L83: yfinance
A84: ADI | B84: Analog Devices Inc | C84: 414.31 | D84: 6181000 | E84: -0.01020113 | F84: -0.01272488 | G84: 0.11538561 | H84: 0.87330149 | I84: 0.99744348 | J84: 1.8318843 | K84: 2026-05-20 04:13 | L84: yfinance
A85: KLAC | B85: KLA Corp | C85: 1740.58 | D85: 1117000 | E85: -0.00903527 | F85: -0.03784384 | G85: -0.02715046 | H85: 1.2258907 | I85: 1.3647739 | J85: 4.843415 | K85: 2026-05-20 04:13 | L85: yfinance
A86: QQQ | B86: INVESCO QQQ TR UNIT SER 1 | C86: 701.53 | D86: 46590800 | E86: -0.00616249 | F86: -0.00807358 | G86: 0.08118988 | H86: 0.35040657 | I86: 0.56993642 | J86: 1.1984199 | K86: 2026-05-20 04:13 | L86: yfinance
A87: BTCI | B87: NEOS ETF TR NEOS BITCOIN HIGH INCOME ETF | C87: 36.16 | D87: 690900 | E87: 0.00249515 | F87: -0.03676082 | G87: 0.0115185 | H87: -0.21447848 | K87: 2026-05-20 04:13 | L87: yfinance
A88: NOSXX | B88: Northern US Government Select MMkt | C88: 1 | K88: 2026-05-20 04:13 | L88: fixed $1.00
A89: HODL | B89: VanEck Bitcoin ETF | C89: 21.71 | D89: 498200 | E89: -0.00046042 | F89: -0.04989065 | G89: -0.00958034 | H89: -0.27318385 | I89: 0.1433838 | K89: 2026-05-20 04:13 | L89: yfinance
A90: IBIT | B90: iShares Bitcoin Trust ETF | C90: 43.5 | D90: 25315200 | E90: -0.00068915 | F90: -0.05021832 | G90: -0.01001362 | H90: -0.27487917 | I90: 0.13636367 | K90: 2026-05-20 04:13 | L90: yfinance
A91: GPIQ | B91: GOLDMAN SACHS ETF TR GOLDMAN SACHS NASDAQ 100 PREMIUM INCOME ETF | C91: 57.04 | D91: 860300 | E91: -0.00401606 | F91: -0.00540536 | G91: 0.06580256 | H91: 0.32384064 | I91: 0.51867862 | K91: 2026-05-20 04:13 | L91: yfinance
A92: IAUI | B92: NEOS ETF TR NEOS GOLD HIGH INCOME ETF | C92: 54.83 | D92: 252300 | E92: -0.0133165 | F92: -0.04109826 | G92: -0.06359982 | K92: 2026-05-20 04:13 | L92: yfinance
A93: AAAU | B93: Goldman Sachs Physical Gold ETF | C93: 44.2 | D93: 1651800 | E93: -0.01646635 | F93: -0.04946235 | G93: -0.07705155 | H93: 0.38341157 | I93: 0.84782611 | J93: 1.364901 | K93: 2026-05-20 04:13 | L93: yfinance
A94: XPAY | B94: ROUNDHILL ETF TRUST ROUNDHILL S&P 500 TARGET 20 MANAGED DISTRIBUTION ETF | C94: 53.32 | D94: 96900 | E94: -0.00540946 | F94: -0.00652131 | G94: 0.03481834 | H94: 0.23758196 | K94: 2026-05-20 04:13 | L94: yfinance
A95: YMAG | B95: TIDAL TRUST II YIELDMAX MAGNIFICENT 7 FUND OF OPTION INCOME ETFS | C95: 12.8 | D95: 1540400 | E95: -0.01081912 | F95: -0.00698217 | G95: 0.02584333 | H95: 0.28501581 | I95: 0.48669012 | K95: 2026-05-20 04:13 | L95: yfinance
A96: FGXXX | B96: First American Government Obligs X | C96: 1 | K96: 2026-05-20 04:13 | L96: fixed $1.00
A97: FBY | B97: YieldMax META Option Income Strategy ETF | C97: 9.99 | D97: 113700 | E97: -0.01089115 | F97: 0.00491084 | G97: -0.08984502 | H97: -0.05066541 | I97: 0.18333711 | K97: 2026-05-20 04:13 | L97: yfinance
A98: NVDY | B98: YieldMax NVDA Option Income Strategy ETF | C98: 14.11 | D98: 3351400 | E98: -0.00633804 | F98: -0.00711949 | G98: 0.05203703 | H98: 0.55688815 | I98: 0.95294657 | K98: 2026-05-20 04:13 | L98: yfinance
A99: MSFO | B99: YieldMax MSFT Option Income Strategy ETF | C99: 12.13 | D99: 180800 | E99: -0.00979591 | F99: 0.01876508 | G99: -0.00903361 | H99: -0.04140219 | I99: 0.01782185 | K99: 2026-05-20 04:13 | L99: yfinance
A100: TSLY | B100: YieldMax TSLA Option Income Strategy ETF | C100: 29.28 | D100: 1457100 | E100: -0.01147874 | F100: -0.05891728 | G100: -0.00420634 | H100: 0.22142492 | I100: 0.72674749 | K100: 2026-05-20 04:13 | L100: yfinance
A101: APLY | B101: YieldMax AAPL Option Income Strategy ETF | C101: 12.61 | D101: 78400 | E101: 0.00158852 | F101: 0.00962687 | G101: 0.08286598 | H101: 0.29771439 | I101: 0.32796828 | K101: 2026-05-20 04:13 | L101: yfinance
A102: AMZY | B102: YieldMax AMZN Option Income Strategy ETF | C102: 11.94 | D102: 1360900 | E102: -0.02131149 | F102: -0.02349417 | G102: 0.02301732 | H102: 0.18615909 | I102: 0.27268257 | K102: 2026-05-20 04:13 | L102: yfinance
A103: GOOY | B103: YieldMax GOOGL Option Income Stgy ETF | C103: 14.96 | D103: 1551100 | E103: -0.01837269 | F103: 0.00371575 | G103: 0.11501613 | H103: 0.98992864 | I103: 0.88082653 | K103: 2026-05-20 04:13 | L103: yfinance
A106: Daily checklist
A107: Total tickers | B107: 98
A108: Tickers with price entered | B108: =COUNT(C6:C103)
A109: Tickers missing price | B109: =B107-B108
A110: Last refresh date | B110: =MAX(K6:K103)
A111: Rows feeding Sheet1 | B111: =ROWS(Sheet1!$A$5:$A$392)

Sheet How to Update
A1: Daily Update Process
A3: Step | B3: What to do | C3: Where | D3: Notes
A4: 1 | B4: Open the Daily Update sheet. | C4: Daily Update | D4: Only edit the yellow columns.
A5: 2 | B5: Update the Workbook last updated date if needed. | C5: Daily Update!B2 | D5: It currently uses =TODAY(), so it changes automatically when opened.
A6: 3 | B6: Paste or type market data for each ticker. | C6: Daily Update columns C:J | D6: Use decimals for percentages if Excel does not auto-convert: 1.5% = 0.015.
A7: 4 | B7: Enter Last Updated and Source/Notes. | C7: Daily Update columns K:L | D7: This helps you know which rows were refreshed.
A8: 5 | B8: Return to Sheet1. | C8: Sheet1 columns G:N | D8: Those columns pull from Daily Update using ticker matching.
A9: 6 | B9: Check the checklist. | C9: Daily Update bottom section | D9: Missing price count should be 0 when your update is complete.
